LICENSE
README.md
setup.py
largesteps/__init__.py
largesteps/geometry.py
largesteps/optimize.py
largesteps/parameterize.py
largesteps/pgf_custom.py
largesteps/solvers.py
largesteps.egg-info/PKG-INFO
largesteps.egg-info/SOURCES.txt
largesteps.egg-info/dependency_links.txt
largesteps.egg-info/requires.txt
largesteps.egg-info/top_level.txt