Metadata-Version: 2.1
Name: largesteps
Version: 0.2.0
Summary: Laplacian parameterization package for shape optimization with differentiable rendering
Home-page: https://github.com/rgl-epfl/large-steps-pytorch
Author: Baptiste Nicolet
Author-email: baptiste.nicolet@epfl.ch
License: BSD
Platform: UNKNOWN
License-File: LICENSE
